tspiral/__init__.py
tspiral/forecasting.py
tspiral/model_selection.py
tspiral-0.3.0.dist-info/LICENSE
tspiral-0.3.0.dist-info/METADATA
tspiral-0.3.0.dist-info/WHEEL
tspiral-0.3.0.dist-info/top_level.txt
tspiral-0.3.0.dist-info/RECORD
