Metadata-Version: 2.1
Name: tspiral
Version: 0.3.0
Summary: A python package for time series forecasting with scikit-learn estimators.
Home-page: https://github.com/cerlymarco/tspiral
Author: Marco Cerliani
Author-email: cerlymarco@gmail.com
License: MIT
Requires-Python: >=3
License-File: LICENSE
Requires-Dist: scikit-learn (>=0.24.2)
Requires-Dist: numpy
Requires-Dist: pandas
